curl_to_json/__init__.py
curl_to_json/__main__.py
curl_to_json/transform.py
curl_to_json-0.1.0.dist-info/METADATA
curl_to_json-0.1.0.dist-info/WHEEL
curl_to_json-0.1.0.dist-info/entry_points.txt
curl_to_json-0.1.0.dist-info/RECORD
