Metadata-Version: 2.1
Name: curl-to-json
Version: 0.1.0
Summary: Convert curl command to json data
Home-page: https://github.com/KingJem/curl-to-json
Author: KingJem
Author-email: qqqivy@gmail.com
Requires-Python: >=3.8,<4.0
Classifier: Programming Language :: Python :: 3
Classifier: Programming Language :: Python :: 3.8
Classifier: Programming Language :: Python :: 3.9
Classifier: Programming Language :: Python :: 3.10
Classifier: Programming Language :: Python :: 3.11
Classifier: Programming Language :: Python :: 3.12
Requires-Dist: six (>=1.16.0,<2.0.0)
Project-URL: Repository, https://github.com/KingJem/curl-to-json
